progress/observability/__init__.py
progress/observability/constants.py
progress/observability/decorators.py
progress/observability/enums.py
progress/observability/exceptions.py
progress/observability/helpers.py
progress/observability/model_fix_processor.py
progress/observability/sdk.py
progress_observability-1.2.0.dist-info/METADATA
progress_observability-1.2.0.dist-info/WHEEL
progress_observability-1.2.0.dist-info/licenses/LICENSE
progress_observability-1.2.0.dist-info/licenses/notices.txt
progress_observability-1.2.0.dist-info/RECORD
