Metadata-Version: 2.4
Name: progress-observability
Version: 1.2.0
Summary: Progress Observability instrumentation for Python agents
Project-URL: Homepage, https://github.com/telerik/agentclarity
Project-URL: Repository, https://github.com/telerik/agentclarity
Project-URL: Documentation, https://docs.telerik.com/agentclarity
Project-URL: Bug Reports, https://github.com/telerik/agentclarity/issues
License: MIT
License-File: LICENSE
License-File: notices.txt
Requires-Python: <4.0.0,>=3.10.0
Requires-Dist: traceloop-sdk==0.49.5
Provides-Extra: dev
Requires-Dist: autopep8>=2.3.1; extra == 'dev'
Requires-Dist: flake8>=7.1.0; extra == 'dev'
